my_sample_package
