Metadata-Version: 1.0
Name: MyPackageTestii
Version: 0.1.1
Summary: This is some stuff that I wrote
Home-page: http://www.example.com/MyPackage
Author: Nobody_Special
Author-email: dev_null@example.com
License: UNKNOWN
Platform: UNKNOWN
